claim_batch/__init__.py
claim_batch/admin.py
claim_batch/apps.py
claim_batch/models.py
claim_batch/schema.py
claim_batch/services.py
claim_batch/test_helpers.py
claim_batch/urls.py
claim_batch/views.py
claim_batch/migrations/0001_initial.py
claim_batch/migrations/0002_capitationpayment.py
claim_batch/migrations/0003_capitationpayment_for_legacy_batch_runs.py
claim_batch/migrations/0004_delete_capitationpayment.py
claim_batch/migrations/0005_capitationpayment.py
claim_batch/migrations/0006_capitationpayment.py
claim_batch/migrations/0007_update_django_scheme_with_missing_fields.py
claim_batch/migrations/0008_set_managed_to_true.py
claim_batch/migrations/__init__.py
claim_batch/reports/__init__.py
claim_batch/reports/pbc_H.py
claim_batch/reports/pbc_P.py
claim_batch/reports/pbh.py
claim_batch/reports/pbp.py
claim_batch/tests/__init__.py
claim_batch/tests/test_graphql.py
openimis_be_claim_batch-1.10.0.dist-info/licenses/LICENSE.md
openimis_be_claim_batch-1.10.0.dist-info/METADATA
openimis_be_claim_batch-1.10.0.dist-info/WHEEL
openimis_be_claim_batch-1.10.0.dist-info/top_level.txt
openimis_be_claim_batch-1.10.0.dist-info/RECORD
